conex/__init__.py
conex/behaviors/__init__.py
conex/behaviors/layer/__init__.py
conex/behaviors/layer/dataset.py
conex/behaviors/network/__init__.py
conex/behaviors/network/neuromodulators.py
conex/behaviors/network/payoff.py
conex/behaviors/network/time_resolution.py
conex/behaviors/neurons/__init__.py
conex/behaviors/neurons/axon.py
conex/behaviors/neurons/dendrite.py
conex/behaviors/neurons/homeostasis.py
conex/behaviors/neurons/setters.py
conex/behaviors/neurons/specs.py
conex/behaviors/neurons/neuron_types/__init__.py
conex/behaviors/neurons/neuron_types/lif_neurons.py
conex/behaviors/synapses/__init__.py
conex/behaviors/synapses/dendrites.py
conex/behaviors/synapses/learning.py
conex/behaviors/synapses/specs.py
conex/helpers/__init__.py
conex/helpers/data.py
conex/helpers/filters.py
conex/helpers/transforms/__init__.py
conex/helpers/transforms/encoders.py
conex/helpers/transforms/masks.py
conex/helpers/transforms/misc.py
conex/nn/__init__.py
conex/nn/priority.py
conex/nn/structure/__init__.py
conex/nn/structure/container.py
conex/nn/structure/cortical_column.py
conex/nn/structure/cortical_layer_connection.py
conex/nn/structure/io_layer.py
conex/nn/structure/layer.py
conex/nn/structure/neocortex.py
conex/nn/structure/port.py
conex/nn/structure/synapsis.py
conex/nn/utils/__init__.py
conex/nn/utils/replication.py
cnrl_conex-0.1.5.dist-info/AUTHORS.rst
cnrl_conex-0.1.5.dist-info/LICENSE
cnrl_conex-0.1.5.dist-info/METADATA
cnrl_conex-0.1.5.dist-info/WHEEL
cnrl_conex-0.1.5.dist-info/top_level.txt
cnrl_conex-0.1.5.dist-info/RECORD
